{
  "total_train_wall_clock_seconds": 13198.286,
  "total_eval_seconds": 4517.711,
  "pure_training_seconds": 8680.575,
  "total_test_seconds": 556.031,
  "epoch_seconds": [
    579.115,
    582.691,
    574.595,
    577.574,
    584.031,
    581.019,
    578.41,
    578.73,
    574.295,
    585.037,
    584.616,
    579.612,
    569.128,
    556.345,
    825.818
  ],
  "eval_seconds": [
    321.868,
    310.933,
    282.467,
    276.922,
    289.277,
    280.942,
    281.887,
    276.186,
    277.956,
    271.52,
    272.145,
    276.84,
    277.057,
    270.696,
    275.845,
    275.17
  ],
  "data_load_seconds": 7.897,
  "model_load_seconds": 0.254,
  "tokenization_seconds": 23.168,
  "total_pipeline_seconds": 13785.636
}